{
    "type": "movie_list",
    "title": "IMDb's Fantasy Top 50",
    "source": "https://wwww.imdb.com",
    "created_by": "lbnt",
    "added": "11/21/25",
    "modified": "11/21/25",
    "ordered_by": "rank",
    "movies": [
        {
            "adult": false,
            "backdrop_path": "/2u7zbn8EudG6kLlBzUYqP8RyFU4.jpg",
            "genre_ids": [
                12,
                14,
                28
            ],
            "id": 122,
            "original_language": "en",
            "original_title": "The Lord of the Rings: The Return of the King",
            "overview": "As armies mass for a final battle that will decide the fate of the world--and powerful, ancient forces of Light and Dark compete to determine the outcome--one member of the Fellowship of the Ring is revealed as the noble heir to the throne of the Kings of Men. Yet, the sole hope for triumph over evil lies with a brave hobbit, Frodo, who, accompanied by his loyal friend Sam and the hideous, wretched Gollum, ventures deep into the very dark heart of Mordor on his seemingly impossible quest to destroy the Ring of Power.\u200b",
            "popularity": 19.3757,
            "poster_path": "/rCzpDGLbOoPwLjy3OAm5NUPOTrC.jpg",
            "release_date": "2003-12-17",
            "title": "The Lord of the Rings: The Return of the King",
            "video": false,
            "vote_average": 8.49,
            "vote_count": 25675
        },
        {
            "adult": false,
            "backdrop_path": "/x2RS3uTcsJJ9IfjNPcgDmukoEcQ.jpg",
            "genre_ids": [
                12,
                14,
                28
            ],
            "id": 120,
            "original_language": "en",
            "original_title": "The Lord of the Rings: The Fellowship of the Ring",
            "overview": "Young hobbit Frodo Baggins, after inheriting a mysterious ring from his uncle Bilbo, must leave his home in order to keep it from falling into the hands of its evil creator. Along the way, a fellowship is formed to protect the ringbearer and make sure that the ring arrives at its final destination: Mt. Doom, the only place where it can be destroyed.",
            "popularity": 21.9789,
            "poster_path": "/6oom5QYQ2yQTMJIbnvbkBL9cHo6.jpg",
            "release_date": "2001-12-18",
            "title": "The Lord of the Rings: The Fellowship of the Ring",
            "video": false,
            "vote_average": 8.425,
            "vote_count": 26608
        },
        {
            "adult": false,
            "backdrop_path": "/kWYfW2Re0rUDE6IHhy4CRuKWeFr.jpg",
            "genre_ids": [
                12,
                14,
                28
            ],
            "id": 121,
            "original_language": "en",
            "original_title": "The Lord of the Rings: The Two Towers",
            "overview": "Frodo Baggins and the other members of the Fellowship continue on their sacred quest to destroy the One Ring--but on separate paths. Their destinies lie at two towers--Orthanc Tower in Isengard, where the corrupt wizard Saruman awaits, and Sauron's fortress at Barad-dur, deep within the dark lands of Mordor. Frodo and Sam are trekking to Mordor to destroy the One Ring of Power while Gimli, Legolas and Aragorn search for the orc-captured Merry and Pippin. All along, nefarious wizard Saruman awaits the Fellowship members at the Orthanc Tower in Isengard.",
            "popularity": 16.5318,
            "poster_path": "/5VTN0pR8gcqV3EPUHHfMGnJYN9L.jpg",
            "release_date": "2002-12-18",
            "title": "The Lord of the Rings: The Two Towers",
            "video": false,
            "vote_average": 8.411,
            "vote_count": 23112
        },
        {
            "adult": false,
            "backdrop_path": "/dMZxEdrWIzUmUoOz2zvmFuutbj7.jpg",
            "genre_ids": [
                12,
                28,
                878
            ],
            "id": 1891,
            "original_language": "en",
            "original_title": "The Empire Strikes Back",
            "overview": "The epic saga continues as Luke Skywalker, in hopes of defeating the evil Galactic Empire, learns the ways of the Jedi from aging master Yoda. But Darth Vader is more determined than ever to capture Luke. Meanwhile, rebel leader Princess Leia, cocky Han Solo, Chewbacca, and droids C-3PO and R2-D2 are thrown into various stages of capture, betrayal and despair.",
            "popularity": 6.3395,
            "poster_path": "/nNAeTmF4CtdSgMDplXTDPOpYzsX.jpg",
            "release_date": "1980-05-20",
            "title": "The Empire Strikes Back",
            "video": false,
            "vote_average": 8.394,
            "vote_count": 17836
        },
        {
            "adult": false,
            "backdrop_path": "/b6HWTOxn1xevvyHU2K9ICvaRU6g.jpg",
            "genre_ids": [
                14,
                18,
                80
            ],
            "id": 497,
            "original_language": "en",
            "original_title": "The Green Mile",
            "overview": "A supernatural tale set on death row in a Southern prison, where gentle giant John Coffey possesses the mysterious power to heal people's ailments. When the cell block's head guard, Paul Edgecomb, recognizes Coffey's miraculous gift, he tries desperately to help stave off the condemned man's execution.",
            "popularity": 12.1888,
            "poster_path": "/o0lO84GI7qrG6XFvtsPOSV7CTNa.jpg",
            "release_date": "1999-12-10",
            "title": "The Green Mile",
            "video": false,
            "vote_average": 8.502,
            "vote_count": 18549
        },
        {
            "adult": false,
            "backdrop_path": "/ukfI9QkU1aIhOhKXYWE9n3z1mFR.jpg",
            "genre_ids": [
                16,
                10751,
                14
            ],
            "id": 129,
            "original_language": "ja",
            "original_title": "\u5343\u3068\u5343\u5c0b\u306e\u795e\u96a0\u3057",
            "overview": "A young girl, Chihiro, becomes trapped in a strange new world of spirits. When her parents undergo a mysterious transformation, she must call upon the courage she never knew she had to free her family.",
            "popularity": 15.7803,
            "poster_path": "/39wmItIWsg5sZMyRUHLkWBcuVCM.jpg",
            "release_date": "2001-07-20",
            "title": "Spirited Away",
            "video": false,
            "vote_average": 8.534,
            "vote_count": 17649
        },
        {
            "adult": false,
            "backdrop_path": "/2w4xG178RpB4MDAIfTkqAuSJzec.jpg",
            "genre_ids": [
                12,
                28,
                878
            ],
            "id": 11,
            "original_language": "en",
            "original_title": "Star Wars",
            "overview": "Princess Leia is captured and held hostage by the evil Imperial forces in their effort to take over the galactic Empire. Venturesome Luke Skywalker and dashing captain Han Solo team together with the loveable robot duo R2-D2 and C-3PO to rescue the beautiful princess and restore peace and justice in the Empire.",
            "popularity": 14.3687,
            "poster_path": "/6FfCtAuVAW8XJjZ7eWeLibRLWTw.jpg",
            "release_date": "1977-05-25",
            "title": "Star Wars",
            "video": false,
            "vote_average": 8.2,
            "vote_count": 21653
        },
        {
            "adult": false,
            "backdrop_path": "/ch3lDc4xQ9MpsNEpnRhvR8PIxxK.jpg",
            "genre_ids": [
                18,
                10751,
                14
            ],
            "id": 1585,
            "original_language": "en",
            "original_title": "It's a Wonderful Life",
            "overview": "A holiday favourite for generations...  George Bailey has spent his entire life giving to the people of Bedford Falls.  All that prevents rich skinflint Mr. Potter from taking over the entire town is George's modest building and loan company.  But on Christmas Eve the business's $8,000 is lost and George's troubles begin.",
            "popularity": 7.6251,
            "poster_path": "/bSqt9rhDZx1Q7UZ86dBPKdNomp2.jpg",
            "release_date": "1946-12-20",
            "title": "It's a Wonderful Life",
            "video": false,
            "vote_average": 8.275,
            "vote_count": 4647
        },
        {
            "adult": false,
            "backdrop_path": "/9xfDWXAUbFXQK585JvByT5pEAhe.jpg",
            "genre_ids": [
                16,
                28,
                12,
                878
            ],
            "id": 569094,
            "original_language": "en",
            "original_title": "Spider-Man: Across the Spider-Verse",
            "overview": "After reuniting with Gwen Stacy, Brooklyn\u2019s full-time, friendly neighborhood Spider-Man is catapulted across the Multiverse, where he encounters the Spider Society, a team of Spider-People charged with protecting the Multiverse\u2019s very existence. But when the heroes clash on how to handle a new threat, Miles finds himself pitted against the other Spiders and must set out on his own to save those he loves most.",
            "popularity": 16.3835,
            "poster_path": "/8Vt6mWEReuy4Of61Lnj5Xj704m8.jpg",
            "release_date": "2023-05-31",
            "title": "Spider-Man: Across the Spider-Verse",
            "video": false,
            "vote_average": 8.338,
            "vote_count": 8035
        },
        {
            "adult": false,
            "backdrop_path": "/wSJHuSD7ojzoXifWjOAjxV7UpEL.jpg",
            "genre_ids": [
                10751,
                16,
                10402,
                12
            ],
            "id": 354912,
            "original_language": "en",
            "original_title": "Coco",
            "overview": "Despite his family\u2019s baffling generations-old ban on music, Miguel dreams of becoming an accomplished musician like his idol, Ernesto de la Cruz. Desperate to prove his talent, Miguel finds himself in the stunning and colorful Land of the Dead following a mysterious chain of events. Along the way, he meets charming trickster Hector, and together, they set off on an extraordinary journey to unlock the real story behind Miguel's family history.",
            "popularity": 20.2476,
            "poster_path": "/6Ryitt95xrO8KXuqRGm1fUuNwqF.jpg",
            "release_date": "2017-10-27",
            "title": "Coco",
            "video": false,
            "vote_average": 8.201,
            "vote_count": 20428
        },
        {
            "adult": false,
            "backdrop_path": "/8x9iKH8kWA0zdkgNdpAew7OstYe.jpg",
            "genre_ids": [
                16,
                10749,
                18
            ],
            "id": 372058,
            "original_language": "ja",
            "original_title": "\u541b\u306e\u540d\u306f\u3002",
            "overview": "High schoolers Mitsuha and Taki are complete strangers living separate lives. But one night, they suddenly switch places. Mitsuha wakes up in Taki\u2019s body, and he in hers. This bizarre occurrence continues to happen randomly, and the two must adjust their lives around each other.",
            "popularity": 24.94,
            "poster_path": "/q719jXXEzOoYaps6babgKnONONX.jpg",
            "release_date": "2016-08-26",
            "title": "Your Name.",
            "video": false,
            "vote_average": 8.479,
            "vote_count": 12109
        },
        {
            "adult": false,
            "backdrop_path": "/8mnXR9rey5uQ08rZAvzojKWbDQS.jpg",
            "genre_ids": [
                16,
                28,
                12,
                878
            ],
            "id": 324857,
            "original_language": "en",
            "original_title": "Spider-Man: Into the Spider-Verse",
            "overview": "Struggling to find his place in the world while juggling school and family, Brooklyn teenager Miles Morales is unexpectedly bitten by a radioactive spider and develops unfathomable powers just like the one and only Spider-Man. While wrestling with the implications of his new abilities, Miles discovers a super collider created by the madman Wilson \"Kingpin\" Fisk, causing others from across the Spider-Verse to be inadvertently transported to his dimension.",
            "popularity": 11.799,
            "poster_path": "/iiZZdoQBEYBv6id8su7ImL0oCbD.jpg",
            "release_date": "2018-12-06",
            "title": "Spider-Man: Into the Spider-Verse",
            "video": false,
            "vote_average": 8.396,
            "vote_count": 16605
        },
        {
            "adult": false,
            "backdrop_path": "/3Rfvhy1Nl6sSGJwyjb0QiZzZYlB.jpg",
            "genre_ids": [
                10751,
                35,
                16,
                12
            ],
            "id": 862,
            "original_language": "en",
            "original_title": "Toy Story",
            "overview": "Led by Woody, Andy's toys live happily in his room until Andy's birthday brings Buzz Lightyear onto the scene. Afraid of losing his place in Andy's heart, Woody plots against Buzz. But when circumstances separate Buzz and Woody from their owner, the duo eventually learns to put aside their differences.",
            "popularity": 16.9865,
            "poster_path": "/uXDfjJbdP4ijW5hWSBrPrlKpxab.jpg",
            "release_date": "1995-11-22",
            "title": "Toy Story",
            "video": false,
            "vote_average": 8.0,
            "vote_count": 19296
        },
        {
            "adult": false,
            "backdrop_path": "/gl0jzn4BupSbL2qMVeqrjKkF9Js.jpg",
            "genre_ids": [
                12,
                14,
                16
            ],
            "id": 128,
            "original_language": "ja",
            "original_title": "\u3082\u306e\u306e\u3051\u59eb",
            "overview": "Ashitaka, a prince of the disappearing Emishi people, is cursed by a demonized boar god and must journey to the west to find a cure. Along the way, he encounters San, a young human woman fighting to protect the forest, and Lady Eboshi, who is trying to destroy it. Ashitaka must find a way to bring balance to this conflict.",
            "popularity": 8.8017,
            "poster_path": "/cMYCDADoLKLbB83g4WnJegaZimC.jpg",
            "release_date": "1997-07-12",
            "title": "Princess Mononoke",
            "video": false,
            "vote_average": 8.326,
            "vote_count": 8608
        },
        {
            "adult": false,
            "backdrop_path": "/wE5JGzujfvDPMIfFjJyrhXFjZLc.jpg",
            "genre_ids": [
                16,
                10751,
                35
            ],
            "id": 10193,
            "original_language": "en",
            "original_title": "Toy Story 3",
            "overview": "Woody, Buzz, and the rest of Andy's toys haven't been played with in years. With Andy about to go to college, the gang find themselves accidentally left at a nefarious day care center. The toys must band together to escape and return home to Andy.",
            "popularity": 13.1717,
            "poster_path": "/AbbXspMOwdvwWZgVN0nabZq03Ec.jpg",
            "release_date": "2010-06-16",
            "title": "Toy Story 3",
            "video": false,
            "vote_average": 7.802,
            "vote_count": 15282
        },
        {
            "adult": false,
            "backdrop_path": "/r2IOBOeg5wLfLtyOnT5Pur6Tl4q.jpg",
            "genre_ids": [
                12,
                28,
                878
            ],
            "id": 1892,
            "original_language": "en",
            "original_title": "Return of the Jedi",
            "overview": "Luke Skywalker leads a mission to rescue his friend Han Solo from the clutches of Jabba the Hutt, while the Emperor seeks to destroy the Rebellion once and for all with a second dreaded Death Star.",
            "popularity": 6.8517,
            "poster_path": "/jQYlydvHm3kUix1f8prMucrplhm.jpg",
            "release_date": "1983-05-25",
            "title": "Return of the Jedi",
            "video": false,
            "vote_average": 7.905,
            "vote_count": 16444
        },
        {
            "adult": false,
            "backdrop_path": "/6G6nqSW9S7EHA9HrYl0Z8uo2H7f.jpg",
            "genre_ids": [
                14,
                18,
                10752
            ],
            "id": 1417,
            "original_language": "es",
            "original_title": "El laberinto del fauno",
            "overview": "In post\u2013civil war Spain, 10-year-old Ofelia moves with her pregnant mother to live under the control of her cruel stepfather. Drawn into a mysterious labyrinth, she meets a faun who reveals that she may be a lost princess from an underground kingdom. To return to her true father, she must complete a series of surreal and perilous tasks that blur the line between reality and fantasy.",
            "popularity": 17.4759,
            "poster_path": "/z7xXihu5wHuSMWymq5VAulPVuvg.jpg",
            "release_date": "2006-10-11",
            "title": "Pan's Labyrinth",
            "video": false,
            "vote_average": 7.757,
            "vote_count": 11108
        },
        {
            "adult": false,
            "backdrop_path": "/tyQo080tijexyUHBvWPwQt26bZa.jpg",
            "genre_ids": [
                28,
                12,
                878
            ],
            "id": 634649,
            "original_language": "en",
            "original_title": "Spider-Man: No Way Home",
            "overview": "Peter Parker is unmasked and no longer able to separate his normal life from the high-stakes of being a super-hero. When he asks for help from Doctor Strange the stakes become even more dangerous, forcing him to discover what it truly means to be Spider-Man.",
            "popularity": 17.603,
            "poster_path": "/1g0dhYtq4irTY1GPXvft6k4YLjm.jpg",
            "release_date": "2021-12-15",
            "title": "Spider-Man: No Way Home",
            "video": false,
            "vote_average": 7.937,
            "vote_count": 21281
        },
        {
            "adult": false,
            "backdrop_path": "/nv5wwZou159v5OC61i4ElR7OqyY.jpg",
            "genre_ids": [
                14,
                16,
                12
            ],
            "id": 4935,
            "original_language": "ja",
            "original_title": "\u30cf\u30a6\u30eb\u306e\u52d5\u304f\u57ce",
            "overview": "Sophie, a young milliner, is turned into an elderly woman by a witch who enters her shop and curses her. She encounters a wizard named Howl and gets caught up in his resistance to fighting for the king.",
            "popularity": 10.3824,
            "poster_path": "/13kOl2v0nD2OLbVSHnHk8GUFEhO.jpg",
            "release_date": "2004-09-09",
            "title": "Howl's Moving Castle",
            "video": false,
            "vote_average": 8.393,
            "vote_count": 10620
        },
        {
            "adult": false,
            "backdrop_path": "/1KgXxv6tHXOnakqYvMPvFwYKWiw.jpg",
            "genre_ids": [
                12,
                35,
                14
            ],
            "id": 762,
            "original_language": "en",
            "original_title": "Monty Python and the Holy Grail",
            "overview": "King Arthur, accompanied by his squire, recruits his Knights of the Round Table, including Sir Bedevere the Wise, Sir Lancelot the Brave, Sir Robin the Not-Quite-So-Brave-As-Sir-Lancelot and Sir Galahad the Pure. On the way, Arthur battles the Black Knight who, despite having had all his limbs chopped off, insists he can still fight. They reach Camelot, but Arthur decides not  to enter, as \"it is a silly place\".",
            "popularity": 5.1549,
            "poster_path": "/7nTkHjETdGMYK1phHwDbPsrzbYl.jpg",
            "release_date": "1975-04-03",
            "title": "Monty Python and the Holy Grail",
            "video": false,
            "vote_average": 7.806,
            "vote_count": 6151
        },
        {
            "adult": false,
            "backdrop_path": "/mlxKite1x1PgmIhJgAxNS9eHmH8.jpg",
            "genre_ids": [
                16,
                10751,
                12,
                35,
                14
            ],
            "id": 508965,
            "original_language": "en",
            "original_title": "Klaus",
            "overview": "A selfish postman and a reclusive toymaker form an unlikely friendship, delivering joy to a cold, dark town that desperately needs it.",
            "popularity": 4.755,
            "poster_path": "/q125RHUDgR4gjwh1QkfYuJLYkL.jpg",
            "release_date": "2019-11-08",
            "title": "Klaus",
            "video": false,
            "vote_average": 8.23,
            "vote_count": 4395
        },
        {
            "adult": false,
            "backdrop_path": "/uRNgkJSkNBFbbn9fPsEjDIy8Sh3.jpg",
            "genre_ids": [
                12,
                14,
                28
            ],
            "id": 22,
            "original_language": "en",
            "original_title": "Pirates of the Caribbean: The Curse of the Black Pearl",
            "overview": "After Port Royal is attacked and pillaged by a mysterious pirate crew, capturing the governor's daughter Elizabeth Swann in the process, William Turner asks free-willing pirate Jack Sparrow to help him locate the crew's ship\u2014The Black Pearl\u2014so that he can rescue the woman he loves.",
            "popularity": 21.2957,
            "poster_path": "/poHwCZeWzJCShH7tOjg8RIoyjcw.jpg",
            "release_date": "2003-07-09",
            "title": "Pirates of the Caribbean: The Curse of the Black Pearl",
            "video": false,
            "vote_average": 7.815,
            "vote_count": 21604
        },
        {
            "adult": false,
            "backdrop_path": "/n5A7brJCjejceZmHyujwUTVgQNC.jpg",
            "genre_ids": [
                12,
                14
            ],
            "id": 12445,
            "original_language": "en",
            "original_title": "Harry Potter and the Deathly Hallows: Part 2",
            "overview": "Harry, Ron and Hermione continue their quest to vanquish the evil Voldemort once and for all. Just as things begin to look hopeless for the young wizards, Harry discovers a trio of magical objects that endow him with powers to rival Voldemort's formidable skills.",
            "popularity": 17.5658,
            "poster_path": "/c54HpQmuwXjHq2C9wmoACjxoom3.jpg",
            "release_date": "2011-07-12",
            "title": "Harry Potter and the Deathly Hallows: Part 2",
            "video": false,
            "vote_average": 8.083,
            "vote_count": 21426
        },
        {
            "adult": false,
            "backdrop_path": "/xgDj56UWyeWQcxQ44f5A3RTWuSs.jpg",
            "genre_ids": [
                16,
                35,
                10751,
                14
            ],
            "id": 2062,
            "original_language": "en",
            "original_title": "Ratatouille",
            "overview": "Remy, a resident of Paris, appreciates good food and has quite a sophisticated palate. He would love to become a chef so he can create and enjoy culinary masterpieces to his heart's delight. The only problem is, Remy is a rat. When he winds up in the sewer beneath one of Paris' finest restaurants, the rodent gourmet finds himself ideally placed to realize his dream.",
            "popularity": 13.9849,
            "poster_path": "/t3vaWRPSf6WjDSamIkKDs1iQWna.jpg",
            "release_date": "2007-06-28",
            "title": "Ratatouille",
            "video": false,
            "vote_average": 7.833,
            "vote_count": 17925
        },
        {
            "adult": false,
            "backdrop_path": "/59vDC1BuEQvti24OMr0ZvtAK6R1.jpg",
            "genre_ids": [
                14,
                12,
                16,
                10751
            ],
            "id": 10191,
            "original_language": "en",
            "original_title": "How to Train Your Dragon",
            "overview": "As the son of a Viking leader on the cusp of manhood, shy Hiccup Horrendous Haddock III faces a rite of passage: he must kill a dragon to prove his warrior mettle. But after downing a feared dragon, he realizes that he no longer wants to destroy it, and instead befriends the beast \u2013 which he names Toothless \u2013 much to the chagrin of his warrior father.",
            "popularity": 11.8927,
            "poster_path": "/ygGmAO60t8GyqUo9xYeYxSZAR3b.jpg",
            "release_date": "2010-03-18",
            "title": "How to Train Your Dragon",
            "video": false,
            "vote_average": 7.9,
            "vote_count": 13886
        },
        {
            "adult": false,
            "backdrop_path": "/sDTnMOJ3H5wI38OxObmCtK7wfd5.jpg",
            "genre_ids": [
                16,
                35,
                10751
            ],
            "id": 585,
            "original_language": "en",
            "original_title": "Monsters, Inc.",
            "overview": "Lovable Sulley and his wisecracking sidekick Mike Wazowski are the top scare team at Monsters, Inc., the scream-processing factory in Monstropolis. When a little girl named Boo wanders into their world, it's the monsters who are scared silly, and it's up to Sulley and Mike to keep her out of sight and get her back home.",
            "popularity": 15.003,
            "poster_path": "/wFSpyMsp7H0ttERbxY7Trlv8xry.jpg",
            "release_date": "2001-11-01",
            "title": "Monsters, Inc.",
            "video": false,
            "vote_average": 7.847,
            "vote_count": 19244
        },
        {
            "adult": false,
            "backdrop_path": "/nRsr98MFztBGm532hCVMGXV6qOp.jpg",
            "genre_ids": [
                12,
                14,
                10751
            ],
            "id": 630,
            "original_language": "en",
            "original_title": "The Wizard of Oz",
            "overview": "Young Dorothy finds herself in a magical world where she makes friends with a lion, a scarecrow and a tin man as they make their way along the yellow brick road to talk with the Wizard and ask for the things they miss most in their lives. The Wicked Witch of the West is the only thing that could stop them.",
            "popularity": 11.8212,
            "poster_path": "/pfAZFD7I2hxW9HCChTuAzsdE6UX.jpg",
            "release_date": "1939-08-15",
            "title": "The Wizard of Oz",
            "video": false,
            "vote_average": 7.591,
            "vote_count": 5896
        },
        {
            "adult": false,
            "backdrop_path": "/jJKZaTBNenlFclQyjrnvzkRmvWE.jpg",
            "genre_ids": [
                16,
                10751,
                12,
                18,
                35
            ],
            "id": 150540,
            "original_language": "en",
            "original_title": "Inside Out",
            "overview": "When 11-year-old Riley moves to a new city, her Emotions team up to help her through the transition. Joy, Fear, Anger, Disgust and Sadness work together, but when Joy and Sadness get lost, they must journey through unfamiliar places to get back home.",
            "popularity": 13.0759,
            "poster_path": "/2H1TmgdfNtsKlU9jKdeNyYL5y8T.jpg",
            "release_date": "2015-06-17",
            "title": "Inside Out",
            "video": false,
            "vote_average": 7.9,
            "vote_count": 22931
        },
        {
            "adult": false,
            "backdrop_path": "/95ozIP0A2fKaAXxwDxUEVn74Iux.jpg",
            "genre_ids": [
                14,
                16,
                10751
            ],
            "id": 8392,
            "original_language": "ja",
            "original_title": "\u3068\u306a\u308a\u306e\u30c8\u30c8\u30ed",
            "overview": "Two sisters move to the country with their father in order to be closer to their hospitalized mother, and discover the surrounding trees are inhabited by Totoros, magical spirits of the forest. When the youngest runs away from home, the older sister seeks help from the spirits to find her.",
            "popularity": 9.6932,
            "poster_path": "/rtGDOeG9LzoerkDGZF9dnVeLppL.jpg",
            "release_date": "1988-04-16",
            "title": "My Neighbor Totoro",
            "video": false,
            "vote_average": 8.1,
            "vote_count": 8465
        },
        {
            "adult": false,
            "backdrop_path": "/6s2BqtDvp1BMiP70zCDU5OW6hMy.jpg",
            "genre_ids": [
                14,
                18
            ],
            "id": 490,
            "original_language": "sv",
            "original_title": "Det sjunde inseglet",
            "overview": "When disillusioned Swedish knight Antonius Block returns home from the Crusades to find his country in the grips of the Black Death, he challenges Death to a chess match for his life. Tormented by the belief that God does not exist, Block sets off on a journey, meeting up with traveling players Jof and his wife, Mia, and becoming determined to evade Death long enough to commit one redemptive act while he still lives.",
            "popularity": 5.5306,
            "poster_path": "/wcZ21zrOsy0b52AfAF50XpTiv75.jpg",
            "release_date": "1957-02-16",
            "title": "The Seventh Seal",
            "video": false,
            "vote_average": 8.167,
            "vote_count": 3209
        },
        {
            "adult": false,
            "backdrop_path": "/oMqgJMCaNIqeJtilc71D4nRqdmt.jpg",
            "genre_ids": [
                16,
                10751,
                18,
                14
            ],
            "id": 110420,
            "original_language": "ja",
            "original_title": "\u304a\u304a\u304b\u307f\u3053\u3069\u3082\u306e\u96e8\u3068\u96ea",
            "overview": "After her werewolf lover unexpectedly dies in an accident, a woman must find a way to raise the son and daughter that she had with him. However, their inheritance of their father's traits prove to be a challenge for her.",
            "popularity": 4.2614,
            "poster_path": "/3Nllh6JgcrFdtOn6iFOWHudNInd.jpg",
            "release_date": "2012-07-21",
            "title": "Wolf Children",
            "video": false,
            "vote_average": 8.2,
            "vote_count": 2394
        },
        {
            "adult": false,
            "backdrop_path": "/iB1tCWl4MKl6OO1kMBD5LxM5BmJ.jpg",
            "genre_ids": [
                14,
                18,
                9648
            ],
            "id": 14696,
            "original_language": "ja",
            "original_title": "\u96e8\u6708\u7269\u8a9e",
            "overview": "In 16th century Japan, peasants Genjuro and Tobei sell their earthenware pots to a group of soldiers in a nearby village, in defiance of a local sage's warning against seeking to profit from warfare. Genjuro's pursuit of both riches and the mysterious Lady Wakasa, as well as Tobei's desire to become a samurai, run the risk of destroying both themselves and their wives, Miyagi and Ohama.",
            "popularity": 2.054,
            "poster_path": "/r8RiuKTIYIJBjczBVsfeP5C00CJ.jpg",
            "release_date": "1953-03-26",
            "title": "Ugetsu",
            "video": false,
            "vote_average": 8.002,
            "vote_count": 621
        },
        {
            "adult": false,
            "backdrop_path": "/bW9fKeoIbq4bDclZ4h9D5BqSqmX.jpg",
            "genre_ids": [
                14,
                18
            ],
            "id": 13188,
            "original_language": "en",
            "original_title": "Scrooge",
            "overview": "Ebenezer Scrooge malcontentedly shuffles through life as a cruel, miserly businessman, until he is visited by three spirits on Christmas Eve who show him how his unhappy childhood and adult behavior has left him a selfish, lonely old man.",
            "popularity": 5.5456,
            "poster_path": "/iUUfQZr87dBQNdyGcmTflAnCPXz.jpg",
            "release_date": "1951-11-30",
            "title": "Scrooge",
            "video": false,
            "vote_average": 7.4,
            "vote_count": 349
        },
        {
            "adult": false,
            "backdrop_path": "/vBOKLF3nhdaKRiCvmdoIUTikG2X.jpg",
            "genre_ids": [
                14,
                18,
                27
            ],
            "id": 10728,
            "original_language": "de",
            "original_title": "Faust - Eine deutsche Volkssage",
            "overview": "God and Satan war over earth; to settle things, they wager on the soul of Faust, a learned and prayerful alchemist.",
            "popularity": 1.2118,
            "poster_path": "/rN703hMFxmkZfyEzsXvFtuFhkXE.jpg",
            "release_date": "1926-10-13",
            "title": "Faust",
            "video": false,
            "vote_average": 7.899,
            "vote_count": 376
        },
        {
            "adult": false,
            "backdrop_path": "/5swI23sPOvSjd5LJ9TQDsMYkCPc.jpg",
            "genre_ids": [
                18,
                35,
                80,
                14
            ],
            "id": 20123,
            "original_language": "sh",
            "original_title": "Dom za ve\u0161anje",
            "overview": "In this luminous tale set in the former Yugoslavia, Perhan, an engaging young Romany with telekinetic powers, is seduced by the quick-cash world of petty crime that threatens to destroy him and those he loves.",
            "popularity": 2.4203,
            "poster_path": "/av6K9MX0jNNFAH6NZVrVV2DMAOA.jpg",
            "release_date": "1988-12-21",
            "title": "Time of the Gypsies",
            "video": false,
            "vote_average": 7.633,
            "vote_count": 412
        },
        {
            "adult": false,
            "backdrop_path": "/s7U6UG12M5K3XPuMCybt7cMRDzm.jpg",
            "genre_ids": [
                12,
                18,
                14
            ],
            "id": 31506,
            "original_language": "de",
            "original_title": "Die Nibelungen: Siegfried",
            "overview": "Siegfried, son of King Siegmund of Xanten, travels to Worms, capital of the Burgundian kingdom, to ask King Gunther for the hand of his sister, the beautiful Kriemhild.",
            "popularity": 1.7213,
            "poster_path": "/rb0mUDrw87WXwH9MsfYvyBxCQ1z.jpg",
            "release_date": "1924-02-14",
            "title": "Die Nibelungen: Siegfried",
            "video": false,
            "vote_average": 7.719,
            "vote_count": 153
        },
        {
            "adult": false,
            "backdrop_path": "/aQ2ZbNqIaecoQsryNe33UmDtms.jpg",
            "genre_ids": [
                12,
                10751,
                14,
                35,
                10749
            ],
            "id": 2493,
            "original_language": "en",
            "original_title": "The Princess Bride",
            "overview": "In this enchantingly cracked fairy tale, the beautiful Princess Buttercup and the dashing Westley must overcome staggering odds to find happiness amid six-fingered swordsmen, murderous princes, Sicilians and rodents of unusual size. But even death can't stop these true lovebirds from triumphing.",
            "popularity": 8.2176,
            "poster_path": "/2FC9L9MrjBoGHYjYZjdWQdopVYb.jpg",
            "release_date": "1987-09-25",
            "title": "The Princess Bride",
            "video": false,
            "vote_average": 7.7,
            "vote_count": 4873
        },
        {
            "adult": false,
            "backdrop_path": "/fW4ZCoEZRBqLAJGFQ2g5AdAfPQR.jpg",
            "genre_ids": [
                10749,
                10751,
                16,
                14
            ],
            "id": 10020,
            "original_language": "en",
            "original_title": "Beauty and the Beast",
            "overview": "Follow the adventures of Belle, a bright young woman who finds herself in the castle of a prince who's been turned into a mysterious beast. With the help of the castle's enchanted staff, Belle soon learns the most important lesson of all -- that true beauty comes from within.",
            "popularity": 10.5567,
            "poster_path": "/hUJ0UvQ5tgE2Z9WpfuduVSdiCiU.jpg",
            "release_date": "1991-10-22",
            "title": "Beauty and the Beast",
            "video": false,
            "vote_average": 7.7,
            "vote_count": 10380
        },
        {
            "adult": false,
            "backdrop_path": "/ttBydD0SynC0TMkW3AcnmsySkLp.jpg",
            "genre_ids": [
                10749,
                14,
                18,
                35
            ],
            "id": 137,
            "original_language": "en",
            "original_title": "Groundhog Day",
            "overview": "A narcissistic TV weatherman, along with his attractive-but-distant producer, and his mawkish cameraman, is sent to report on Groundhog Day in the small town of Punxsutawney, where he finds himself repeating the same day over and over.",
            "popularity": 8.3174,
            "poster_path": "/gCgt1WARPZaXnq523ySQEUKinCs.jpg",
            "release_date": "1993-02-11",
            "title": "Groundhog Day",
            "video": false,
            "vote_average": 7.618,
            "vote_count": 8499
        },
        {
            "adult": false,
            "backdrop_path": "/nenJjvfe2Eq8uBMXFJnWj5mw4bi.jpg",
            "genre_ids": [
                16,
                10751,
                12,
                14,
                10749
            ],
            "id": 812,
            "original_language": "en",
            "original_title": "Aladdin",
            "overview": "In the boorish city of Agrabah, kind-hearted street urchin Aladdin and Princess Jasmine fall in love, although she can only marry a prince. He and power-hungry Grand Vizier Jafar vie for a magic lamp that can fulfill their wishes.",
            "popularity": 7.6683,
            "poster_path": "/eLFfl7vS8dkeG1hKp5mwbm37V83.jpg",
            "release_date": "1992-11-25",
            "title": "Aladdin",
            "video": false,
            "vote_average": 7.7,
            "vote_count": 11685
        },
        {
            "adult": false,
            "backdrop_path": "/rQaHA74pevnGsxcKGaoZVGWe9TC.jpg",
            "genre_ids": [
                16,
                10751,
                35,
                14,
                18
            ],
            "id": 508442,
            "original_language": "en",
            "original_title": "Soul",
            "overview": "Joe Gardner is a middle school teacher with a love for jazz music. After a successful audition at the Half Note Club, he suddenly gets into an accident that separates his soul from his body and is transported to the You Seminar, a center in which souls develop and gain passions before being transported to a newborn child. Joe must enlist help from the other souls-in-training, like 22, a soul who has spent eons in the You Seminar, in order to get back to Earth.",
            "popularity": 9.0711,
            "poster_path": "/pEz5aROvfy5FBW1OTlrDO3VryWO.jpg",
            "release_date": "2020-12-25",
            "title": "Soul",
            "video": false,
            "vote_average": 8.103,
            "vote_count": 11025
        },
        {
            "adult": false,
            "backdrop_path": "/fK40VGYIm7hmKrLJ26fgPQU0qRG.jpg",
            "genre_ids": [
                16,
                878,
                28
            ],
            "id": 149,
            "original_language": "ja",
            "original_title": "AKIRA",
            "overview": "A secret military project endangers Neo-Tokyo when it turns a biker gang member into a rampaging psychic psychopath that only two teenagers and a group of psychics can stop.",
            "popularity": 7.8334,
            "poster_path": "/neZ0ykEsPqxamsX6o5QNUFILQrz.jpg",
            "release_date": "1988-06-10",
            "title": "Akira",
            "video": false,
            "vote_average": 7.938,
            "vote_count": 4557
        },
        {
            "adult": false,
            "backdrop_path": "/3zTbERSBLh7waK9811RTKGAcG86.jpg",
            "genre_ids": [
                16,
                10751,
                12,
                14
            ],
            "id": 441130,
            "original_language": "en",
            "original_title": "Wolfwalkers",
            "overview": "In a time of superstition and magic, when wolves are seen as demonic and nature an evil to be tamed, a young apprentice hunter comes to Ireland with her father to wipe out the last pack. But when she saves a wild native girl, their friendship leads her to discover the world of the Wolfwalkers and transform her into the very thing her father is tasked to destroy.",
            "popularity": 11.7235,
            "poster_path": "/vqGiNbdc2sDwsnivMMYzwAoSSu6.jpg",
            "release_date": "2020-10-26",
            "title": "Wolfwalkers",
            "video": false,
            "vote_average": 8.205,
            "vote_count": 1305
        },
        {
            "adult": false,
            "backdrop_path": "/z6OZ2Q4FYELeGoBj9tVDWCvevkj.jpg",
            "genre_ids": [
                12,
                14,
                16,
                28,
                10751
            ],
            "id": 10515,
            "original_language": "ja",
            "original_title": "\u5929\u7a7a\u306e\u57ce\u30e9\u30d4\u30e5\u30bf",
            "overview": "A young boy and a girl with a magic crystal must race against pirates and foreign agents in a search for a legendary floating castle.",
            "popularity": 8.6885,
            "poster_path": "/41XxSsJc5OrulP0m7TrrUeO2hoz.jpg",
            "release_date": "1986-08-02",
            "title": "Castle in the Sky",
            "video": false,
            "vote_average": 7.967,
            "vote_count": 4482
        },
        {
            "adult": false,
            "backdrop_path": "/mVLZvSe1Aa8CFKx0cInTamVZJrW.jpg",
            "genre_ids": [
                10751,
                16,
                14
            ],
            "id": 110416,
            "original_language": "en",
            "original_title": "Song of the Sea",
            "overview": "The story of the last Seal Child\u2019s journey home. After their mother\u2019s disappearance, Ben and Saoirse are sent to live with Granny in the city. When they resolve to return to their home by the sea, their journey becomes a race against time as they are drawn into a world Ben knows only from his mother\u2019s folktales. But this is no bedtime story; these fairy folk have been in our world far too long. It soon becomes clear to Ben that Saoirse is the key to their survival.",
            "popularity": 4.8587,
            "poster_path": "/16LQC6zpqB0l74mVWb93a2oMFnX.jpg",
            "release_date": "2014-06-23",
            "title": "Song of the Sea",
            "video": false,
            "vote_average": 7.999,
            "vote_count": 1516
        },
        {
            "adult": false,
            "backdrop_path": "/imUJOrtNf8EWameChpaRLXSaX4w.jpg",
            "genre_ids": [
                16,
                18,
                14
            ],
            "id": 149871,
            "original_language": "ja",
            "original_title": "\u304b\u3050\u3084\u59eb\u306e\u7269\u8a9e",
            "overview": "Found inside a shining stalk of bamboo by an old bamboo cutter and his wife, a tiny girl grows rapidly into an exquisite young lady. The mysterious young princess enthrals all who encounter her. But, ultimately, she must confront her fate.",
            "popularity": 2.7942,
            "poster_path": "/mWRQNlWXYYfd2z4FRm99MsgHgiA.jpg",
            "release_date": "2013-11-23",
            "title": "The Tale of The Princess Kaguya",
            "video": false,
            "vote_average": 8.086,
            "vote_count": 1902
        },
        {
            "adult": false,
            "backdrop_path": "/2nerKhF40OzjnGGOyzHcsAw8T53.jpg",
            "genre_ids": [
                35,
                18,
                10752
            ],
            "id": 11902,
            "original_language": "sr",
            "original_title": "\u041f\u043e\u0434\u0437\u0435\u043c\u0459\u0435",
            "overview": "A group of Serbian socialists prepares for the war in a surreal underground filled by parties, tragedies, love and hate.",
            "popularity": 1.5433,
            "poster_path": "/h8N6y13t4VusrDdH5PzTkwvBvgN.jpg",
            "release_date": "1995-05-13",
            "title": "Underground",
            "video": false,
            "vote_average": 7.727,
            "vote_count": 731
        },
        {
            "adult": false,
            "backdrop_path": "/Ag4eANWzHEwC7rQVyvcGsL34ieP.jpg",
            "genre_ids": [
                10402,
                18
            ],
            "id": 12104,
            "original_language": "en",
            "original_title": "Pink Floyd: The Wall",
            "overview": "A troubled rock star descends into madness in the midst of his physical and social isolation from everyone.",
            "popularity": 1.8341,
            "poster_path": "/aElHyIdF5jmctFGhlhhaPFsbBJC.jpg",
            "release_date": "1982-07-14",
            "title": "Pink Floyd: The Wall",
            "video": false,
            "vote_average": 7.942,
            "vote_count": 1585
        },
        {
            "adult": false,
            "backdrop_path": "/wJ4HyVZsbZRWH7BS3bLZsvO31rZ.jpg",
            "genre_ids": [
                35,
                18,
                14
            ],
            "id": 29264,
            "original_language": "es",
            "original_title": "El \u00e1ngel exterminador",
            "overview": "A formal dinner party starts out normally enough, but after the bourgeois group retire to the host\u2019s music room, they inexplicably find themselves unable to leave.",
            "popularity": 2.5574,
            "poster_path": "/qqZXHvBFxUpo8Pfbyvgh4SYMiWm.jpg",
            "release_date": "1962-05-16",
            "title": "The Exterminating Angel",
            "video": false,
            "vote_average": 7.9,
            "vote_count": 699
        },
        {
            "adult": false,
            "backdrop_path": "/5HPPIHg9lEyH1rvzi5bAAbo2RxW.jpg",
            "genre_ids": [
                10749,
                14,
                18,
                35
            ],
            "id": 28162,
            "original_language": "en",
            "original_title": "A Matter of Life and Death",
            "overview": "A British wartime aviator who cheats death must argue for his life before a celestial court, hoping to prolong his fledgling romance with an American girl.",
            "popularity": 2.8771,
            "poster_path": "/H74LWKnhOeIFSk9gNjBcPjIov3.jpg",
            "release_date": "1946-12-15",
            "title": "A Matter of Life and Death",
            "video": false,
            "vote_average": 7.751,
            "vote_count": 445
        }
    ]
}